bpyth/__init__.py
bpyth/__main__.py
bpyth/bpyth_files.py
bpyth/bpyth_human.py
bpyth/bpyth_iterable.py
bpyth/bpyth_object_analysis.py
bpyth/bpyth_string.py
bpyth/bpyth_tools.py
bpyth-0.2.2.dist-info/licenses/LICENSE
bpyth-0.2.2.dist-info/METADATA
bpyth-0.2.2.dist-info/WHEEL
bpyth-0.2.2.dist-info/entry_points.txt
bpyth-0.2.2.dist-info/top_level.txt
bpyth-0.2.2.dist-info/RECORD
