Metadata-Version: 2.4
Name: bpyth
Version: 0.2.2
Summary: Various Python Tools
Author-email: djekra <hopsalla@gmail.com>
License: MIT
Project-URL: Homepage, https://github.com/djekra/bpyth
Classifier: Programming Language :: Python :: 3
Classifier: License :: OSI Approved :: MIT License
Classifier: Operating System :: OS Independent
Requires-Python: >=3.10
License-File: LICENSE
Requires-Dist: blab<0.3.0,>=0.2.1
Dynamic: license-file
